kholodov_hist
