Metadata-Version: 2.1
Name: kholodov-hist
Version: 0.1
Summary: dummy projec
Home-page: UNKNOWN
Author-email: ksteklo@mail.ru
License: UNKNOWN
Platform: UNKNOWN
